odoo/addons/sale_line_refund_to_invoice_qty/README.rst
odoo/addons/sale_line_refund_to_invoice_qty/__init__.py
odoo/addons/sale_line_refund_to_invoice_qty/__manifest__.py
odoo/addons/sale_line_refund_to_invoice_qty/i18n/es.po
odoo/addons/sale_line_refund_to_invoice_qty/i18n/it.po
odoo/addons/sale_line_refund_to_invoice_qty/i18n/sale_line_refund_to_invoice_qty.pot
odoo/addons/sale_line_refund_to_invoice_qty/migrations/14.0.2.0.1/post-fix-old-field-value.py
odoo/addons/sale_line_refund_to_invoice_qty/models/__init__.py
odoo/addons/sale_line_refund_to_invoice_qty/models/account.py
odoo/addons/sale_line_refund_to_invoice_qty/models/res_company.py
odoo/addons/sale_line_refund_to_invoice_qty/models/res_config_settings.py
odoo/addons/sale_line_refund_to_invoice_qty/models/sale.py
odoo/addons/sale_line_refund_to_invoice_qty/readme/CONTRIBUTORS.rst
odoo/addons/sale_line_refund_to_invoice_qty/readme/DESCRIPTION.rst
odoo/addons/sale_line_refund_to_invoice_qty/readme/USAGE.rst
odoo/addons/sale_line_refund_to_invoice_qty/static/description/icon.png
odoo/addons/sale_line_refund_to_invoice_qty/static/description/index.html
odoo/addons/sale_line_refund_to_invoice_qty/tests/__init__.py
odoo/addons/sale_line_refund_to_invoice_qty/tests/test_sale_line_refund_to_invoice_qty.py
odoo/addons/sale_line_refund_to_invoice_qty/views/account_move_views.xml
odoo/addons/sale_line_refund_to_invoice_qty/views/res_config_settings_views.xml
odoo/addons/sale_line_refund_to_invoice_qty/views/sale_order_views.xml
odoo/addons/sale_line_refund_to_invoice_qty/wizards/__init__.py
odoo/addons/sale_line_refund_to_invoice_qty/wizards/account_move_reversal.py
odoo/addons/sale_line_refund_to_invoice_qty/wizards/account_move_reversal_view.xml
odoo14_addon_sale_line_refund_to_invoice_qty-14.0.2.1.0.dist-info/METADATA
odoo14_addon_sale_line_refund_to_invoice_qty-14.0.2.1.0.dist-info/WHEEL
odoo14_addon_sale_line_refund_to_invoice_qty-14.0.2.1.0.dist-info/top_level.txt
odoo14_addon_sale_line_refund_to_invoice_qty-14.0.2.1.0.dist-info/RECORD
